rspyenv/__init__.py
rspyenv/env.py
rspyenv-0.1.1.dist-info/METADATA
rspyenv-0.1.1.dist-info/WHEEL
rspyenv-0.1.1.dist-info/RECORD
