Metadata-Version: 2.3
Name: rspyenv
Version: 0.1.1
Summary: A light python package for managing environment variables.
License: MIT
Author: Reza Shirazi
Author-email: itreza7@gmail.com
Requires-Python: >=3.11,<4.0
Classifier: License :: OSI Approved :: MIT License
Classifier: Programming Language :: Python :: 3
Classifier: Programming Language :: Python :: 3.11
Classifier: Programming Language :: Python :: 3.12
Classifier: Programming Language :: Python :: 3.13
Project-URL: Repository, https://github.com/itreza7/rspyenv
